AUTHOR.txt
CHANGES.txt
LICENSE.txt
buildout.cfg
setup.py
src/falkolab/__init__.py
src/falkolab.ext3.layer.egg-info/PKG-INFO
src/falkolab.ext3.layer.egg-info/SOURCES.txt
src/falkolab.ext3.layer.egg-info/dependency_links.txt
src/falkolab.ext3.layer.egg-info/namespace_packages.txt
src/falkolab.ext3.layer.egg-info/not-zip-safe
src/falkolab.ext3.layer.egg-info/requires.txt
src/falkolab.ext3.layer.egg-info/top_level.txt
src/falkolab/ext3/__init__.py
src/falkolab/ext3/layer/README.txt
src/falkolab/ext3/layer/__init__.py
src/falkolab/ext3/layer/configure.zcml
src/falkolab/ext3/layer/interfaces.py
src/falkolab/ext3/layer/views.py